docs_mcp/__init__.py
docs_mcp/documentation.py
docs_mcp/parsers.py
docs_mcp/server.py
snapdepdoc-0.1.0.dist-info/METADATA
snapdepdoc-0.1.0.dist-info/WHEEL
snapdepdoc-0.1.0.dist-info/entry_points.txt
snapdepdoc-0.1.0.dist-info/licenses/LICENSE
snapdepdoc-0.1.0.dist-info/RECORD
