Metadata-Version: 2.4
Name: snapdepdoc
Version: 0.1.0
Summary: Snapshot your dependencies, access version-perfect documentation - An MCP server for AI development assistance
Project-URL: Homepage, https://github.com/thec0dewriter/docs_mcp
Project-URL: Repository, https://github.com/thec0dewriter/docs_mcp
Project-URL: Issues, https://github.com/thec0dewriter/docs_mcp/issues
Author: SnapDepDoc contributors
License: MIT
License-File: LICENSE
Keywords: ai-assistant,dependencies,documentation,mcp,package-manager,snapdepdoc
Classifier: Development Status :: 3 - Alpha
Classifier: Intended Audience :: Developers
Classifier: License :: OSI Approved :: MIT License
Classifier: Programming Language :: Python :: 3
Classifier: Programming Language :: Python :: 3.10
Classifier: Programming Language :: Python :: 3.11
Classifier: Programming Language :: Python :: 3.12
Classifier: Topic :: Software Development :: Documentation
Classifier: Topic :: Software Development :: Libraries
Requires-Python: >=3.10
Requires-Dist: httpx>=0.27.0
Requires-Dist: mcp[cli]>=1.2.0
Requires-Dist: packaging>=24.0
Requires-Dist: toml>=0.10.2
Provides-Extra: dev
Requires-Dist: black>=24.0.0; extra == 'dev'
Requires-Dist: pytest-asyncio>=0.23.0; extra == 'dev'
Requires-Dist: pytest>=8.0.0; extra == 'dev'
Requires-Dist: ruff>=0.3.0; extra == 'dev'
